Verilog-VDU/cell_automaton.v
// Verilog HDL for "COMP32211", "drawing_dummy" "functional"
// This is an inactive cell which takes the place of a drawing function.
// It 'ties off' outputs tidily.

`define TPD 2

module cell_automaton(input  wire        clk,
                      input  wire        req,
                      output reg         ack,
                      output wire        busy,
                      output wire        de_req,
                      input  wire        de_ack,
                      output wire [17:0] de_addr,
                      output wire  [3:0] de_nbyte,
                      output wire [31:0] de_w_data);


reg [3:0] nbyte;
reg [17:0] addr;
reg int_req, int_busy;
reg [7:0] addr_A,addr_B,addr_C,addr_D,addr_E,addr_F;
reg [3:0] A, B, C, D, E, F;
reg RAM_r, RAM_w, stall;

//contnuous assignment
assign busy = int_busy;
assign de_addr = addr;
assign de_req = int_req;
assign de_nbyte = nbyte;
assign de_w_data = 32'hFFFF_FFFF;

//RAM on the FPGA
reg [3:0] block_RAM_A [0:159];
reg [3:0] block_RAM_B [0:159];
reg [3:0] block_RAM_C [0:159];
reg [3:0] block_RAM_D [0:159];
reg [3:0] block_RAM_E [0:159];
reg [3:0] block_RAM_F [0:159];
reg [1:0] stage;
reg line;

/* Line Ordering
* 1 -> Writing and Calculating ABC, Reading DEF
* 0 -> Writing and Calculating DEF, Reading ABC
*/

/* Stage Ordering
* 00 -> Write C
     -> Calculate A
     -> Read F

* 01 -> Write A 
     -> Calculate B
     -> Read D

* 10 -> Write B
     -> Calculate C
     -> Read E
*/

//for reads from RAM-> read data in preparation for next stage
always @ (posedge clk) begin 
  if(!stall && RAM_r) begin
    if (line) begin
      case(stage)
      2'b00:   begin
        F = block_RAM_F[addr_F];
        addr_F += 3; end
      2'b01:   begin
        D = block_RAM_D[addr_D];
        addr_D += 3; end
      default: begin
        E = block_RAM_E[addr_E];
        addr_E += 3; end
      endcase
    end
    if (!line) begin
      case(stage)
      2'b00:   begin
        C = block_RAM_C[addr_C];
        addr_C += 3; end
      2'b01:   begin
        A = block_RAM_A[addr_A];
        addr_A += 3; end
      default: begin
        B = block_RAM_B[addr_B];
        addr_B += 3; end
      endcase
    end
    RAM_r = 0;
  end
end

//for memory writes to the VDU
always @ (posedge clk) begin
  @ (addr);
  int_req = 1;
  stall = 1;
  @(de_ack);
  stall = 0;
  int_req = 0;
end 

//for writes to RAM-> write data calculated previous stage
always @ (posedge clk) begin
  if (!stall && RAM_w) begin
    if (line) begin
      case(stage)
      2'b00:   begin
        block_RAM_C[addr_C] = C;
        nbyte = C;
        addr_C += 3; end
      2'b01:   begin
        block_RAM_A[addr_A] = A;
        nbyte = A;
        addr_A += 3; end
      default: begin
        block_RAM_B[addr_B] = B;
        nbyte = B;
        addr_B += 3; end
      endcase
    end
    if (!line) begin
      case(stage)
      2'b00:   begin
        block_RAM_F[addr_F] = F;
        nbyte = F;
        addr_F += 3; end
      2'b01:   begin
        block_RAM_D[addr_D] = D;
        nbyte = D;
        addr_D += 3; end
      default: begin
        block_RAM_E[addr_E] = E;
        nbyte = E;
        addr_E += 3; end 
      endcase
    end
    addr += 1;
    RAM_w = 0;
  end
end

//for calculation -> calculate current
always @ (posedge clk) begin
  if (!stall) begin
    if (line) begin
      case(stage)
      2'b00:   A = newline({F[3],D[3:0],E[0]});
      2'b01:   B = newline({D[3],E[3:0],F[0]});
      default: C = newline({E[3],F[3:0],D[0]});
      endcase
    end
    if (!line) begin
      case(stage)
      2'b00:   A = newline({C[3],A[3:0],B[0]});
      2'b01:   B = newline({A[3],B[3:0],C[0]});
      default: C = newline({B[3],C[3:0],A[0]});
      endcase
    end
  end
end

//Detecting End of Line Switches
always @ (posedge clk) begin
  if ((line) && (addr_A >= 640) && (addr_B >= 640) && (addr_C >= 640)) line = !(line);
  if ((!line) && (addr_D >= 640) && (addr_E >= 640) && (addr_F >= 640)) line = !(line);
end 

//Resetting at the end of the line
always @ (line) begin
  addr_A = 0;
  addr_B = 1;
  addr_C = -1;
  addr_D = 0;
  addr_E = 1;
  addr_F = -1;
  A = block_RAM_A[addr_A];
  B = block_RAM_B[addr_B];
  D = block_RAM_D[addr_D];
  E = block_RAM_E[addr_E];
  C = 4'b0000; 
  F = 4'b0000;
  stage = 2'b00; 
end

//Creating a new set of 4 pixels
function [3:0] newline (input [5:0] previous);
begin
  newline[0] = rules(previous[2:0]);
  newline[1] = rules(previous[3:1]);
  newline[2] = rules(previous[4:2]);
  newline[3] = rules(previous[5:3]);
end
endfunction

//Induvidual Pixel Rules
function rules (input [2:0] previous); 
begin
  case(previous)
  3'b000:  rules = 0;
  3'b001:  rules = 1;
  3'b010:  rules = 1;
  3'b100:  rules = 1;
  3'b011:  rules = 0;
  3'b101:  rules = 0;
  3'b110:  rules = 1;
  3'b111:  rules = 0;
  default: rules = 0;
  endcase
end 
endfunction

//Stage FSM
always @ (negedge clk) begin
  if (int_busy && !stall) begin
    case(stage)
    2'b00: stage = 2'b01;
    2'b01: stage = 2'b10;
    2'b10: stage = 2'b00; 
    endcase
    RAM_r = 1; 
    RAM_w = 1;
  end
end 


always @ (posedge clk) begin
  if (req) begin
    stage = 2'b00;
    line  = 0;
    ack   = 1;
    int_busy  = 1; 
    stall = 0;
    end 
  else begin
    ack = 0; end                     
end

initial 
begin
  line = 1; 
  int_busy = 0;
  int_req = 0;
  ack = 0;
  addr = 0;
  nbyte = 4'b1111;
  $readmemh("initial.mem", block_RAM_A);
  $readmemh("initial.mem", block_RAM_B);
  $readmemh("initial.mem", block_RAM_C);
  $readmemh("initial.mem", block_RAM_D);
  $readmemh("initial.mem", block_RAM_E);
  $readmemh("initial.mem", block_RAM_F);
end 

endmodule

Verilog-VDU/cell_automaton_tb.v

// Verilog stimulus file.
//The Clock with a frequency of 40ns
/*
initial
  begin
    clk = 0; 
    forever #20 clk = !clk; 
$stop;
end

integer file_handle; 
reg fake_req;
reg allow_memory;
reg [15:0] xs, ys, xe, ye;

task error_handler (input [3:0] error); 
    begin 
        case (error)  
          0: $fdisplay(file_handle, "req allowed to interrupt while busy at time %t", $time);//
          1: $fdisplay(file_handle, "memory didnt wait for permission from de_ack at %t ", $time);//
          2: $fdisplay(file_handle, "Early start error at time %t ", $time );//
          3: $fdisplay(file_handle, "acknowldge/busy error at time %t ", $time );//
          4: $fdisplay(file_handle, "de_req error at time %t ", $time );//
          default: $fdisplay(file_handle, "Unknown error at time %t ", $time);
        endcase
    end
endtask

//does the unit wait until input request to start ? 
always @ (posedge busy, posedge ack) begin
  if (!(req)) error_handler(2);
end 

// does the unit acknowledge the request properly?
always @ (posedge req) begin
  if (!fake_req) begin
    #1 if (!busy) error_handler(3);
    if (!ack) error_handler(3);

    #40 if (!(busy)) error_handler(3);
    if (ack) error_handler(3);
  end
end


// does the unit request permission to begin memory access?
always @ (posedge busy) begin 
  #40 if (de_req != 1'b1) error_handler(4);
end

//responding to de_req responses
always @ (posedge de_req) begin
    if(de_req === 1) begin
      @(posedge clk);
      while (de_req) begin
        #40 de_ack = !de_ack;
      end
    end
  de_ack = 0; 
end 


always @ (posedge de_ack) begin
  allow_memory = 1;
end

//does the unit wait for de_ack to write to memory
always @ (de_addr, de_data, de_nbyte) begin
  #10 if (allow_memory == 0) error_handler(1);
  allow_memory = 0;
end

//checking to see if req can be allowed to alter/interrupt when busy
always @ (posedge busy) begin
  #80 repeat($random & 3) @(posedge clk);
  r0 = 0; r1 = 0; r2 = 0; r3 = 0; r6 = 0;
  fake_req = 1; req = 1; 
  if ((de_addr == 0) || (de_data == 0)) error_handler(0);
  #40 req = 0; fake_req = 0;
end

always @ (posedge de_req) begin 
  $fdisplay(,file_handle,"%b", de_nbyte);
  if ((de_addr+1)%640 == 0) $fdisplay(file_handle,"\n");
    
end

task test();
  begin
    //Setting Up
    de_ack = 1;
    #40 de_ack = 0;
    #40 allow_memory = 1; req = 1;
    @(ack);
    #40 req = 0;
  end
endtask

initial
  begin
  file_handle = $fopen("output.txt");
  #100
    @(posedge clk);
    test();
    @(negedge busy);
    $stop;

    @(posedge clk);
    test();
    @(negedge busy);
    $stop;
  
  $fclose(file_handle);
  #100 $finish;
end
*/

`timescale 1ns/100ps

module cell_automaton_tb ();
  reg clk, req;
  wire ack;
  wire busy, de_req;
  reg de_ack;
  wire [17:0] de_addr;
  wire  [3:0] de_nbyte;
  wire [31:0] de_w_data;
  integer file_handle; 
  reg fake_req;
  reg allow_memory;
  reg [15:0] xs, ys, xe, ye;

cell_automaton ca (clk, req, ack, busy, de_req, de_ack, de_addr, de_nbyte, de_w_data);

//The Clock with a frequency of 40ns
initial
  begin
    clk = 0; 
    forever #20 clk = !clk; 
$stop;
end

initial
begin
  #20000 $finish; 
end

//responding to de_req responses
always @ (posedge de_req) begin
    if(de_req === 1) begin
      @(posedge clk);
      while (de_req) begin
        #40 de_ack = !de_ack;
      end
    end
  de_ack = 0; 
end 

//Tests task, that runs a test
task test();
  begin
    //Setting Up
    de_ack = 1;
    #40 de_ack = 0;
    #40 allow_memory = 1; req = 1;
    @(ack);
    #40 req = 0;
  end
endtask

always @ (posedge de_ack) begin
  allow_memory = 1;
end

always @ (posedge de_req) begin 
  $fdisplay(file_handle,"%b", de_nbyte);
  if ((de_addr+1)%640 == 0) $fdisplay(file_handle,"\n");
end

//Driver Block for tests
initial
  begin
  file_handle = $fopen("output.txt");
  #100
    @(posedge clk);
    test();
    @(negedge busy);
    $stop;
  $fclose(file_handle);
  #100 $finish;
end

initial 
begin
  $dumpfile("cell_automaton_tb_results.vcd");
  $dumpvars;
end
endmodule

Verilog-VDU/cell_automaton_tb_results.vcd
$date
	Fri Nov 25 16:05:42 2022
$end
$version
	Icarus Verilog
$end
$timescale
	100ps
$end
$scope module cell_automaton_tb $end
$var wire 32 ! de_w_data [31:0] $end
$var wire 1 " de_req $end
$var wire 4 # de_nbyte [3:0] $end
$var wire 18 $ de_addr [17:0] $end
$var wire 1 % busy $end
$var wire 1 & ack $end
$var reg 1 ' allow_memory $end
$var reg 1 ( clk $end
$var reg 1 ) de_ack $end
$var reg 1 * req $end
$var integer 32 + file_handle [31:0] $end
$scope module ca $end
$var wire 1 % busy $end
$var wire 1 ( clk $end
$var wire 1 ) de_ack $end
$var wire 18 , de_addr [17:0] $end
$var wire 4 - de_nbyte [3:0] $end
$var wire 1 " de_req $end
$var wire 32 . de_w_data [31:0] $end
$var wire 1 * req $end
$var reg 4 / A [3:0] $end
$var reg 4 0 B [3:0] $end
$var reg 4 1 C [3:0] $end
$var reg 4 2 D [3:0] $end
$var reg 4 3 E [3:0] $end
$var reg 4 4 F [3:0] $end
$var reg 1 5 RAM_r $end
$var reg 1 6 RAM_w $end
$var reg 1 & ack $end
$var reg 18 7 addr [17:0] $end
$var reg 8 8 addr_A [7:0] $end
$var reg 8 9 addr_B [7:0] $end
$var reg 8 : addr_C [7:0] $end
$var reg 8 ; addr_D [7:0] $end
$var reg 8 < addr_E [7:0] $end
$var reg 8 = addr_F [7:0] $end
$var reg 1 > int_busy $end
$var reg 1 ? int_req $end
$var reg 1 @ line $end
$var reg 4 A nbyte [3:0] $end
$var reg 2 B stage [1:0] $end
$var reg 1 C stall $end
$scope function newline $end
$var reg 4 D newline [3:0] $end
$var reg 6 E previous [5:0] $end
$upscope $end
$scope function rules $end
$var reg 3 F previous [2:0] $end
$var reg 1 G rules $end
$upscope $end
$upscope $end
$scope task test $end
$upscope $end
$upscope $end
$enddefinitions $end
#0
$dumpvars
xG
bx F
bx E
bx D
xC
b0 B
b1111 A
1@
0?
0>
b11111111 =
b1 <
b0 ;
b11111111 :
b1 9
b0 8
b0 7
x6
x5
b0 4
b0 3
b0 2
b0 1
b0 0
b0 /
b11111111111111111111111111111111 .
b1111 -
b0 ,
b10 +
x*
x)
0(
x'
0&
0%
b0 $
b1111 #
0"
b11111111111111111111111111111111 !
$end
#200
1(
#400
0(
#600
1(
#800
0(
#1000
1'
1)
1(
#1200
0(
#1400
1(
0)
#1600
0(
#1800
b0 D
0G
b0 F
b0 E
0C
1%
1>
1&
0@
1(
1*
#2000
16
15
b1 B
0(
#2200
1C
1"
1?
0&
06
b1 $
b1 ,
b1 7
b11 ;
b0 #
b0 -
b0 A
05
b11 8
1(
0*
#2400
0(
#2600
1(
#2800
0(
#3000
0"
0?
0C
1(
1)
#3200
16
15
b10 B
0(
#3400
05
b100 9
06
b10 $
b10 ,
b10 7
b100 <
1(
0)
#3600
16
15
b0 B
0(
#3800
1C
1"
1?
bx00 F
bx00000 E
06
b11 $
b11 ,
b11 7
b10 =
05
b10 :
bx 1
1(
#4000
0(
#4200
1(
#4400
0(
#4600
bx00 F
0"
0?
0C
1(
1)
#4800
16
15
b1 B
0(
#5000
05
b110 8
06
b100 $
b100 ,
b100 7
b110 ;
b0 F
b0x E
1(
0)
#5200
16
15
b10 B
0(
#5400
1C
1"
1?
b0 1
b0xx F
b0xxxx0 E
06
b101 $
b101 ,
b101 7
b111 <
05
b111 9
1(
#5600
0(
#5800
1(
#6000
0(
#6200
b0 F
b0 E
0"
0?
0C
1(
1)
#6400
16
15
b0 B
0(
#6600
05
b101 :
06
b110 $
b110 ,
b110 7
b101 =
1(
0)
#6800
16
15
b1 B
0(
#7000
1C
1"
1?
06
b111 $
b111 ,
b111 7
b1001 ;
05
b1001 8
1(
#7200
0(
#7400
1(
#7600
0(
#7800
0"
0?
0C
1(
1)
#8000
16
15
b10 B
0(
#8200
05
b1010 9
06
b1000 $
b1000 ,
b1000 7
b1010 <
1(
0)
#8400
16
15
b0 B
0(
#8600
1C
1"
1?
06
b1001 $
b1001 ,
b1001 7
b1000 =
05
b1000 :
1(
#8800
0(
#9000
1(
#9200
0(
#9400
0"
0?
0C
1(
1)
#9600
16
15
b1 B
0(
#9800
05
b1100 8
06
b1010 $
b1010 ,
b1010 7
b1100 ;
1(
0)
#10000
16
15
b10 B
0(
#10200
1C
1"
1?
06
b1011 $
b1011 ,
b1011 7
b1101 <
05
b1101 9
1(
#10400
0(
#10600
1(
#10800
0(
#11000
0"
0?
0C
1(
1)
#11200
16
15
b0 B
0(
#11400
05
b1011 :
06
b1100 $
b1100 ,
b1100 7
b1011 =
1(
0)
#11600
16
15
b1 B
0(
#11800
1C
1"
1?
06
b1101 $
b1101 ,
b1101 7
b1111 ;
05
b1111 8
1(
#12000
0(
#12200
1(
#12400
0(
#12600
0"
0?
0C
1(
1)
#12800
16
15
b10 B
0(
#13000
05
b10000 9
06
b1110 $
b1110 ,
b1110 7
b10000 <
1(
0)
#13200
16
15
b0 B
0(
#13400
1C
1"
1?
06
b1111 $
b1111 ,
b1111 7
b1110 =
05
b1110 :
1(
#13600
0(
#13800
1(
#14000
0(
#14200
0"
0?
0C
1(
1)
#14400
16
15
b1 B
0(
#14600
05
b10010 8
06
b10000 $
b10000 ,
b10000 7
b10010 ;
1(
0)
#14800
16
15
b10 B
0(
#15000
1C
1"
1?
06
b10001 $
b10001 ,
b10001 7
b10011 <
05
b10011 9
1(
#15200
0(
#15400
1(
#15600
0(
#15800
0"
0?
0C
1(
1)
#16000
16
15
b0 B
0(
#16200
05
b10001 :
06
b10010 $
b10010 ,
b10010 7
b10001 =
1(
0)
#16400
16
15
b1 B
0(
#16600
1C
1"
1?
06
b10011 $
b10011 ,
b10011 7
b10101 ;
05
b10101 8
1(
#16800
0(
#17000
1(
#17200
0(
#17400
0"
0?
0C
1(
1)
#17600
16
15
b10 B
0(
#17800
05
b10110 9
06
b10100 $
b10100 ,
b10100 7
b10110 <
1(
0)
#18000
16
15
b0 B
0(
#18200
1C
1"
1?
06
b10101 $
b10101 ,
b10101 7
b10100 =
05
b10100 :
1(
#18400
0(
#18600
1(
#18800
0(
#19000
0"
0?
0C
1(
1)
#19200
16
15
b1 B
0(
#19400
05
b11000 8
06
b10110 $
b10110 ,
b10110 7
b11000 ;
1(
0)
#19600
16
15
b10 B
0(
#19800
1C
1"
1?
06
b10111 $
b10111 ,
b10111 7
b11001 <
05
b11001 9
1(
#20000
0(
#20200
1(
#20400
0(
#20600
0"
0?
0C
1(
1)
#20800
16
15
b0 B
0(
#21000
05
b10111 :
06
b11000 $
b11000 ,
b11000 7
b10111 =
1(
0)
#21200
16
15
b1 B
0(
#21400
1C
1"
1?
06
b11001 $
b11001 ,
b11001 7
b11011 ;
05
b11011 8
1(
#21600
0(
#21800
1(
#22000
0(
#22200
0"
0?
0C
1(
1)
#22400
16
15
b10 B
0(
#22600
05
b11100 9
06
b11010 $
b11010 ,
b11010 7
b11100 <
1(
0)
#22800
16
15
b0 B
0(
#23000
1C
1"
1?
06
b11011 $
b11011 ,
b11011 7
b11010 =
05
b11010 :
1(
#23200
0(
#23400
1(
#23600
0(
#23800
0"
0?
0C
1(
1)
#24000
16
15
b1 B
0(
#24200
05
b11110 8
06
b11100 $
b11100 ,
b11100 7
b11110 ;
1(
0)
#24400
16
15
b10 B
0(
#24600
1C
1"
1?
06
b11101 $
b11101 ,
b11101 7
b11111 <
05
b11111 9
1(
#24800
0(
#25000
1(
#25200
0(
#25400
0"
0?
0C
1(
1)
#25600
16
15
b0 B
0(
#25800
05
b11101 :
06
b11110 $
b11110 ,
b11110 7
b11101 =
1(
0)
#26000
16
15
b1 B
0(
#26200
1C
1"
1?
06
b11111 $
b11111 ,
b11111 7
b100001 ;
05
b100001 8
1(
#26400
0(
#26600
1(
#26800
0(
#27000
0"
0?
0C
1(
1)
#27200
16
15
b10 B
0(
#27400
05
b100010 9
06
b100000 $
b100000 ,
b100000 7
b100010 <
1(
0)
#27600
16
15
b0 B
0(
#27800
1C
1"
1?
06
b100001 $
b100001 ,
b100001 7
b100000 =
05
b100000 :
1(
#28000
0(
#28200
1(
#28400
0(
#28600
0"
0?
0C
1(
1)
#28800
16
15
b1 B
0(
#29000
05
b100100 8
06
b100010 $
b100010 ,
b100010 7
b100100 ;
1(
0)
#29200
16
15
b10 B
0(
#29400
1C
1"
1?
06
b100011 $
b100011 ,
b100011 7
b100101 <
05
b100101 9
1(
#29600
0(
#29800
1(
#30000
0(
#30200
0"
0?
0C
1(
1)
#30400
16
15
b0 B
0(
#30600
05
b100011 :
06
b100100 $
b100100 ,
b100100 7
b100011 =
1(
0)
#30800
16
15
b1 B
0(
#31000
1C
1"
1?
06
b100101 $
b100101 ,
b100101 7
b100111 ;
05
b100111 8
1(
#31200
0(
#31400
1(
#31600
0(
#31800
0"
0?
0C
1(
1)
#32000
16
15
b10 B
0(
#32200
05
b101000 9
06
b100110 $
b100110 ,
b100110 7
b101000 <
1(
0)
#32400
16
15
b0 B
0(
#32600
1C
1"
1?
06
b100111 $
b100111 ,
b100111 7
b100110 =
05
b100110 :
1(
#32800
0(
#33000
1(
#33200
0(
#33400
0"
0?
0C
1(
1)
#33600
16
15
b1 B
0(
#33800
05
b101010 8
06
b101000 $
b101000 ,
b101000 7
b101010 ;
1(
0)
#34000
16
15
b10 B
0(
#34200
1C
1"
1?
06
b101001 $
b101001 ,
b101001 7
b101011 <
05
b101011 9
1(
#34400
0(
#34600
1(
#34800
0(
#35000
0"
0?
0C
1(
1)
#35200
16
15
b0 B
0(
#35400
05
b101001 :
06
b101010 $
b101010 ,
b101010 7
b101001 =
1(
0)
#35600
16
15
b1 B
0(
#35800
1C
1"
1?
06
b101011 $
b101011 ,
b101011 7
b101101 ;
05
b101101 8
1(
#36000
0(
#36200
1(
#36400
0(
#36600
0"
0?
0C
1(
1)
#36800
16
15
b10 B
0(
#37000
05
b101110 9
06
b101100 $
b101100 ,
b101100 7
b101110 <
1(
0)
#37200
16
15
b0 B
0(
#37400
1C
1"
1?
06
b101101 $
b101101 ,
b101101 7
b101100 =
05
b101100 :
1(
#37600
0(
#37800
1(
#38000
0(
#38200
0"
0?
0C
1(
1)
#38400
16
15
b1 B
0(
#38600
05
b110000 8
06
b101110 $
b101110 ,
b101110 7
b110000 ;
1(
0)
#38800
16
15
b10 B
0(
#39000
1C
1"
1?
06
b101111 $
b101111 ,
b101111 7
b110001 <
05
b110001 9
1(
#39200
0(
#39400
1(
#39600
0(
#39800
0"
0?
0C
1(
1)
#40000
16
15
b0 B
0(
#40200
05
b101111 :
06
b110000 $
b110000 ,
b110000 7
b101111 =
1(
0)
#40400
16
15
b1 B
0(
#40600
1C
1"
1?
06
b110001 $
b110001 ,
b110001 7
b110011 ;
05
b110011 8
1(
#40800
0(
#41000
1(
#41200
0(
#41400
0"
0?
0C
1(
1)
#41600
16
15
b10 B
0(
#41800
05
b110100 9
06
b110010 $
b110010 ,
b110010 7
b110100 <
1(
0)
#42000
16
15
b0 B
0(
#42200
1C
1"
1?
06
b110011 $
b110011 ,
b110011 7
b110010 =
05
b110010 :
1(
#42400
0(
#42600
1(
#42800
0(
#43000
0"
0?
0C
1(
1)
#43200
16
15
b1 B
0(
#43400
05
b110110 8
06
b110100 $
b110100 ,
b110100 7
b110110 ;
1(
0)
#43600
16
15
b10 B
0(
#43800
1C
1"
1?
06
b110101 $
b110101 ,
b110101 7
b110111 <
05
b110111 9
1(
#44000
0(
#44200
1(
#44400
0(
#44600
0"
0?
0C
1(
1)
#44800
16
15
b0 B
0(
#45000
05
b110101 :
06
b110110 $
b110110 ,
b110110 7
b110101 =
1(
0)
#45200
16
15
b1 B
0(
#45400
1C
1"
1?
06
b110111 $
b110111 ,
b110111 7
b111001 ;
05
b111001 8
1(
#45600
0(
#45800
1(
#46000
0(
#46200
0"
0?
0C
1(
1)
#46400
16
15
b10 B
0(
#46600
05
b111010 9
06
b111000 $
b111000 ,
b111000 7
b111010 <
1(
0)
#46800
16
15
b0 B
0(
#47000
1C
1"
1?
06
b111001 $
b111001 ,
b111001 7
b111000 =
05
b111000 :
1(
#47200
0(
#47400
1(
#47600
0(
#47800
0"
0?
0C
1(
1)
#48000
16
15
b1 B
0(
#48200
05
b111100 8
06
b111010 $
b111010 ,
b111010 7
b111100 ;
1(
0)
#48400
16
15
b10 B
0(
#48600
1C
1"
1?
06
b111011 $
b111011 ,
b111011 7
b111101 <
05
b111101 9
1(
#48800
0(
#49000
1(
#49200
0(
#49400
0"
0?
0C
1(
1)
#49600
16
15
b0 B
0(
#49800
05
b111011 :
06
b111100 $
b111100 ,
b111100 7
b111011 =
1(
0)
#50000
16
15
b1 B
0(
#50200
1C
1"
1?
06
b111101 $
b111101 ,
b111101 7
b111111 ;
05
b111111 8
1(
#50400
0(
#50600
1(
#50800
0(
#51000
0"
0?
0C
1(
1)
#51200
16
15
b10 B
0(
#51400
05
b1000000 9
06
b111110 $
b111110 ,
b111110 7
b1000000 <
1(
0)
#51600
16
15
b0 B
0(
#51800
1C
1"
1?
06
b111111 $
b111111 ,
b111111 7
b111110 =
05
b111110 :
1(
#52000
0(
#52200
1(
#52400
0(
#52600
0"
0?
0C
1(
1)
#52800
16
15
b1 B
0(
#53000
05
b1000010 8
06
b1000000 $
b1000000 ,
b1000000 7
b1000010 ;
1(
0)
#53200
16
15
b10 B
0(
#53400
1C
1"
1?
06
b1000001 $
b1000001 ,
b1000001 7
b1000011 <
05
b1000011 9
1(
#53600
0(
#53800
1(
#54000
0(
#54200
0"
0?
0C
1(
1)
#54400
16
15
b0 B
0(
#54600
05
b1000001 :
06
b1000010 $
b1000010 ,
b1000010 7
b1000001 =
1(
0)
#54800
16
15
b1 B
0(
#55000
1C
1"
1?
06
b1000011 $
b1000011 ,
b1000011 7
b1000101 ;
05
b1000101 8
1(
#55200
0(
#55400
1(
#55600
0(
#55800
0"
0?
0C
1(
1)
#56000
16
15
b10 B
0(
#56200
05
b1000110 9
06
b1000100 $
b1000100 ,
b1000100 7
b1000110 <
1(
0)
#56400
16
15
b0 B
0(
#56600
1C
1"
1?
06
b1000101 $
b1000101 ,
b1000101 7
b1000100 =
05
b1000100 :
1(
#56800
0(
#57000
1(
#57200
0(
#57400
0"
0?
0C
1(
1)
#57600
16
15
b1 B
0(
#57800
05
b1001000 8
06
b1000110 $
b1000110 ,
b1000110 7
b1001000 ;
1(
0)
#58000
16
15
b10 B
0(
#58200
1C
1"
1?
06
b1000111 $
b1000111 ,
b1000111 7
b1001001 <
05
b1001001 9
1(
#58400
0(
#58600
1(
#58800
0(
#59000
0"
0?
0C
1(
1)
#59200
16
15
b0 B
0(
#59400
05
b1000111 :
06
b1001000 $
b1001000 ,
b1001000 7
b1000111 =
1(
0)
#59600
16
15
b1 B
0(
#59800
1C
1"
1?
06
b1001001 $
b1001001 ,
b1001001 7
b1001011 ;
05
b1001011 8
1(
#60000
0(
#60200
1(
#60400
0(
#60600
0"
0?
0C
1(
1)
#60800
16
15
b10 B
0(
#61000
05
b1001100 9
06
b1001010 $
b1001010 ,
b1001010 7
b1001100 <
1(
0)
#61200
16
15
b0 B
0(
#61400
1C
1"
1?
06
b1001011 $
b1001011 ,
b1001011 7
b1001010 =
05
b1001010 :
1(
#61600
0(
#61800
1(
#62000
0(
#62200
0"
0?
0C
1(
1)
#62400
16
15
b1 B
0(
#62600
05
b1001110 8
06
b1001100 $
b1001100 ,
b1001100 7
b1001110 ;
1(
0)
#62800
16
15
b10 B
0(
#63000
1C
1"
1?
06
b1001101 $
b1001101 ,
b1001101 7
b1001111 <
05
b1001111 9
1(
#63200
0(
#63400
1(
#63600
0(
#63800
0"
0?
0C
1(
1)
#64000
16
15
b0 B
0(
#64200
05
b1001101 :
06
b1001110 $
b1001110 ,
b1001110 7
b1001101 =
1(
0)
#64400
16
15
b1 B
0(
#64600
1C
1"
1?
06
b1001111 $
b1001111 ,
b1001111 7
b1010001 ;
05
b1010001 8
1(
#64800
0(
#65000
1(
#65200
0(
#65400
0"
0?
0C
1(
1)
#65600
16
15
b10 B
0(
#65800
05
b1010010 9
06
b1010000 $
b1010000 ,
b1010000 7
b1010010 <
1(
0)
#66000
16
15
b0 B
0(
#66200
1C
1"
1?
06
b1010001 $
b1010001 ,
b1010001 7
b1010000 =
05
b1010000 :
1(
#66400
0(
#66600
1(
#66800
0(
#67000
0"
0?
0C
1(
1)
#67200
16
15
b1 B
0(
#67400
05
b1010100 8
06
b1010010 $
b1010010 ,
b1010010 7
b1010100 ;
1(
0)
#67600
16
15
b10 B
0(
#67800
1C
1"
1?
06
b1010011 $
b1010011 ,
b1010011 7
b1010101 <
05
b1010101 9
1(
#68000
0(
#68200
1(
#68400
0(
#68600
0"
0?
0C
1(
1)
#68800
16
15
b0 B
0(
#69000
05
b1010011 :
06
b1010100 $
b1010100 ,
b1010100 7
b1010011 =
1(
0)
#69200
16
15
b1 B
0(
#69400
1C
1"
1?
06
b1010101 $
b1010101 ,
b1010101 7
b1010111 ;
05
b1010111 8
1(
#69600
0(
#69800
1(
#70000
0(
#70200
0"
0?
0C
1(
1)
#70400
16
15
b10 B
0(
#70600
05
b1011000 9
06
b1010110 $
b1010110 ,
b1010110 7
b1011000 <
1(
0)
#70800
16
15
b0 B
0(
#71000
1C
1"
1?
06
b1010111 $
b1010111 ,
b1010111 7
b1010110 =
05
b1010110 :
1(
#71200
0(
#71400
1(
#71600
0(
#71800
0"
0?
0C
1(
1)
#72000
16
15
b1 B
0(
#72200
05
b1011010 8
06
b1011000 $
b1011000 ,
b1011000 7
b1011010 ;
1(
0)
#72400
16
15
b10 B
0(
#72600
1C
1"
1?
06
b1011001 $
b1011001 ,
b1011001 7
b1011011 <
05
b1011011 9
1(
#72800
0(
#73000
1(
#73200
0(
#73400
0"
0?
0C
1(
1)
#73600
16
15
b0 B
0(
#73800
05
b1011001 :
06
b1011010 $
b1011010 ,
b1011010 7
b1011001 =
1(
0)
#74000
16
15
b1 B
0(
#74200
1C
1"
1?
06
b1011011 $
b1011011 ,
b1011011 7
b1011101 ;
05
b1011101 8
1(
#74400
0(
#74600
1(
#74800
0(
#75000
0"
0?
0C
1(
1)
#75200
16
15
b10 B
0(
#75400
05
b1011110 9
06
b1011100 $
b1011100 ,
b1011100 7
b1011110 <
1(
0)
#75600
16
15
b0 B
0(
#75800
1C
1"
1?
06
b1011101 $
b1011101 ,
b1011101 7
b1011100 =
05
b1011100 :
1(
#76000
0(
#76200
1(
#76400
0(
#76600
0"
0?
0C
1(
1)
#76800
16
15
b1 B
0(
#77000
05
b1100000 8
06
b1011110 $
b1011110 ,
b1011110 7
b1100000 ;
1(
0)
#77200
16
15
b10 B
0(
#77400
1C
1"
1?
06
b1011111 $
b1011111 ,
b1011111 7
b1100001 <
05
b1100001 9
1(
#77600
0(
#77800
1(
#78000
0(
#78200
0"
0?
0C
1(
1)
#78400
16
15
b0 B
0(
#78600
05
b1011111 :
06
b1100000 $
b1100000 ,
b1100000 7
b1011111 =
1(
0)
#78800
16
15
b1 B
0(
#79000
1C
1"
1?
06
b1100001 $
b1100001 ,
b1100001 7
b1100011 ;
05
b1100011 8
1(
#79200
0(
#79400
1(
#79600
0(
#79800
0"
0?
0C
1(
1)
#80000
16
15
b10 B
0(
#80200
05
b1100100 9
06
b1100010 $
b1100010 ,
b1100010 7
b1100100 <
1(
0)
#80400
16
15
b0 B
0(
#80600
1C
1"
1?
06
b1100011 $
b1100011 ,
b1100011 7
b1100010 =
05
b1100010 :
1(
#80800
0(
#81000
1(
#81200
0(
#81400
0"
0?
0C
1(
1)
#81600
16
15
b1 B
0(
#81800
05
b1100110 8
06
b1100100 $
b1100100 ,
b1100100 7
b1100110 ;
1(
0)
#82000
16
15
b10 B
0(
#82200
1C
1"
1?
06
b1100101 $
b1100101 ,
b1100101 7
b1100111 <
05
b1100111 9
1(
#82400
0(
#82600
1(
#82800
0(
#83000
0"
0?
0C
1(
1)
#83200
16
15
b0 B
0(
#83400
05
b1100101 :
06
b1100110 $
b1100110 ,
b1100110 7
b1100101 =
1(
0)
#83600
16
15
b1 B
0(
#83800
1C
1"
1?
06
b1100111 $
b1100111 ,
b1100111 7
b1101001 ;
05
b1101001 8
1(
#84000
0(
#84200
1(
#84400
0(
#84600
0"
0?
0C
1(
1)
#84800
16
15
b10 B
0(
